<ns0:test-suite xmlns:ns0="urn:model.allure.qatools.yandex.ru" start="1533216055885" stop="1533216055893">
  <name>test_sample</name>
  <labels/>
  <test-cases>
    <test-case start="1533216055885" status="passed" stop="1533216055893">
      <name>test_answer</name>
      <attachments/>
      <labels>
        <label name="severity" value="normal"/>
        <label name="thread" value="9680-MainThread"/>
        <label name="host" value="1JH32W2X7UE9PLP"/>
        <label name="framework" value="pytest"/>
        <label name="language" value="cpython3"/>
      </labels>
      <steps/>
    </test-case>
  </test-cases>
</ns0:test-suite>
